[
  { "id": 1,  "title": "Always On My Mind (Let U Go)", "artist": "Sound for Someone", "url": "/sound for someone/Always On My Mind (Let U Go).mp3" },
  { "id": 2,  "title": "Desire",                       "artist": "Sound for Someone", "url": "/sound for someone/Desire.mp3" },
  { "id": 3,  "title": "Don't Wake Me Up",             "artist": "Sound for Someone", "url": "/sound for someone/Don't Wake Me Up.mp3" },
  { "id": 4,  "title": "Feel It In My",                "artist": "Sound for Someone", "url": "/sound for someone/Feel it in My.mp3" },
  { "id": 5,  "title": "I'm Not Alone 2019 Edit",      "artist": "Sound for Someone", "url": "/sound for someone/I'm Not Alone - 2019 Edit.mp3" },
  { "id": 6,  "title": "I've Arrived",                 "artist": "Sound for Someone", "url": "/sound for someone/I've Arrived (with Tomike).mp3" },
  { "id": 7,  "title": "It Gets Better Forever Mix",   "artist": "Sound for Someone", "url": "/sound for someone/It Gets Better - Forever Mix.mp3" },
  { "id": 8,  "title": "Just Feels Tight",             "artist": "Sound for Someone", "url": "/sound for someone/Just Feels Tight.mp3" },
  { "id": 9,  "title": "Savana",                       "artist": "Sound for Someone", "url": "/sound for someone/Savana.mp3" },
  { "id": 10, "title": "What's A Girl To Do",          "artist": "Sound for Someone", "url": "/sound for someone/What's A Girl To Do.mp3" },
  { "id": 11, "title": "World Hold On FISHER Rework",  "artist": "Sound for Someone", "url": "/sound for someone/World, Hold On - FISHER Rework.mp3" },
  { "id": 12, "title": "Yosemite",                     "artist": "Sound for Someone", "url": "/sound for someone/Yosemite.mp3" }
]
